deecubes/__init__.py
deecubes/constants.py
deecubes/deecubes.py
deecubes/shortener.py
deecubes/utils.py
deecubes-0.3.1.dist-info/DESCRIPTION.rst
deecubes-0.3.1.dist-info/METADATA
deecubes-0.3.1.dist-info/RECORD
deecubes-0.3.1.dist-info/WHEEL
deecubes-0.3.1.dist-info/entry_points.txt
deecubes-0.3.1.dist-info/metadata.json
deecubes-0.3.1.dist-info/top_level.txt
