Metadata-Version: 2.0
Name: deecubes
Version: 0.3.1
Summary: deecubes (DSSS - Damn Simple Static url Shortener)
Home-page: https://github.com/shantanugoel/deecubes/
Author: Shantanu Goel
Author-email: shantanu@shantanugoel.com
License: MIT
Keywords: url shorturl url-shortener
Platform: UNKNOWN
Classifier: Development Status :: 4 - Beta
Classifier: License :: OSI Approved :: MIT License
Classifier: Operating System :: POSIX
Classifier: Natural Language :: English
Classifier: Operating System :: OS Independent
Classifier: Programming Language :: Python
Classifier: Programming Language :: Python :: 3
Classifier: Programming Language :: Python :: 3.4
Classifier: Programming Language :: Python :: 3.5
Classifier: Programming Language :: Python :: 3.6
Classifier: Topic :: Internet
Classifier: Topic :: Software Development :: Libraries
Classifier: Topic :: Software Development :: Libraries :: Python Modules
Classifier: Topic :: Utilities
Requires-Python: >=3
